<?xml version="1.0" encoding="UTF-8" standalone="yes"?>
<jornada num="37">
	<partido>
		<equipoLocal nombre="Real Madrid" totalGoles="2">
			<gol dorsal="9" minuto="2"/>
			<gol dorsal="3" minuto="35"/>
			<tarjeta tipo="AMARILLA" dorsal="1"/>
		</equipoLocal>
		<equipoVisitante nombre= "FC Barcelona" totalGoles="2">
			<gol dorsal="7" minuto="34"/>
			<gol dorsal="3" minuto="80"/>
			<tarjeta tipo="AMARILLA" dorsal="1"/>
		</equipoVisitante>
	</partido>
	
	<partido>
		<equipoLocal nombre="Atletico de Madrid" totalGoles="2">
			<gol dorsal="8" minuto="6"/>
			<gol dorsal="3" minuto="28"/>
			<tarjeta tipo="AMARILLA" dorsal="1"/>
		</equipoLocal>
		<equipoVisitante nombre= "Valencia CF" totalGoles="0">
			<tarjeta tipo="ROJA" dorsal="1"/>
		</equipoVisitante>
	</partido>
	
</jornada>
